lefdef/__init__.py
lefdef/_def.py
lefdef/_lef.py
lefdef/def_reader.py
lefdef/lef_reader.py
lefdef/lib/lefdef.dll
lefdef/lib/lefdef.lib
lefdef/lib/liblefdef.dll
lefdef/lib/liblefdef.dll.a
lefdef/lib/liblefdef.so
lefdef-0.6.0.dist-info/LICENSE
lefdef-0.6.0.dist-info/METADATA
lefdef-0.6.0.dist-info/WHEEL
lefdef-0.6.0.dist-info/top_level.txt
lefdef-0.6.0.dist-info/RECORD
