Metadata-Version: 2.1
Name: lefdef
Version: 0.6.0
Summary: A Python library for reading and writing LEF and DEF files.
Home-page: https://github.com/ruykaji/lefdef-python
Author: ruykaji
License: MIT
Platform: UNKNOWN
Classifier: Development Status :: 3 - Alpha
Classifier: Intended Audience :: Developers
Classifier: License :: OSI Approved :: MIT License
Classifier: Programming Language :: Python :: 3
Classifier: Programming Language :: Python :: 3.6
Classifier: Programming Language :: Python :: 3.7
Classifier: Programming Language :: Python :: 3.8
Classifier: Programming Language :: Python :: 3.9
License-File: LICENSE
